relic/__init__.py
relic/common.py
relic/config.py
relic/ucs.py
relic/chunky/__init__.py
relic/chunky/serializer.py
relic/chunky/chunk/__init__.py
relic/chunky/chunk/chunk.py
relic/chunky/chunk/header.py
relic/chunky/chunky/__init__.py
relic/chunky/chunky/chunky.py
relic/chunky/chunky/header.py
relic/chunky_formats/__init__.py
relic/chunky_formats/convertable.py
relic/chunky_formats/converter.py
relic/chunky_formats/protocols.py
relic/chunky_formats/util.py
relic/chunky_formats/dow/__init__.py
relic/chunky_formats/dow/converter.py
relic/chunky_formats/dow/events.py
relic/chunky_formats/dow/rgd.py
relic/chunky_formats/dow/rml.py
relic/chunky_formats/dow/rsh.py
relic/chunky_formats/dow/rtx.py
relic/chunky_formats/dow/sgb.py
relic/chunky_formats/dow/tmp.py
relic/chunky_formats/dow/whe.py
relic/chunky_formats/dow/common_chunks/__init__.py
relic/chunky_formats/dow/common_chunks/fbif.py
relic/chunky_formats/dow/common_chunks/imag.py
relic/chunky_formats/dow/common_chunks/imag_writer.py
relic/chunky_formats/dow/common_chunks/skel_chunk_nonwhm.py
relic/chunky_formats/dow/fda/__init__.py
relic/chunky_formats/dow/fda/audio_converter.py
relic/chunky_formats/dow/fda/chunky.py
relic/chunky_formats/dow/fda/conv/dec.exe
relic/chunky_formats/dow/fda/conv/enc.exe
relic/chunky_formats/dow/sgm/__init__.py
relic/chunky_formats/dow/sgm/obj_writer.py
relic/chunky_formats/dow/sgm/sgm.py
relic/chunky_formats/dow/whm/__init__.py
relic/chunky_formats/dow/whm/animation.py
relic/chunky_formats/dow/whm/json_writer.py
relic/chunky_formats/dow/whm/mesh.py
relic/chunky_formats/dow/whm/obj_writer.py
relic/chunky_formats/dow/whm/shared.py
relic/chunky_formats/dow/whm/whm.py
relic/chunky_formats/dow/wtp/__init__.py
relic/chunky_formats/dow/wtp/writer.py
relic/chunky_formats/dow/wtp/wtp.py
relic/chunky_formats/dow2/__init__.py
relic/chunky_formats/dow2/converter.py
relic/chunky_formats/dow2/model/__init__.py
relic/chunky_formats/dow2/model/json_writer.py
relic/chunky_formats/dow2/model/model.py
relic_game_tool-2022.0a8.dist-info/LICENSE.txt
relic_game_tool-2022.0a8.dist-info/METADATA
relic_game_tool-2022.0a8.dist-info/WHEEL
relic_game_tool-2022.0a8.dist-info/entry_points.txt
relic_game_tool-2022.0a8.dist-info/top_level.txt
relic_game_tool-2022.0a8.dist-info/RECORD
