Metadata-Version: 2.1
Name: relic-game-tool
Version: 2022.0a8
Summary: A library for unpacking and extracting Relic SGA and Relic Chunky files.
Home-page: https://github.com/ModernMAK/Relic-Game-Tool
Author: Marcus Kertesz
License: UNKNOWN
Project-URL: Bug Tracker, https://github.com/ModernMAK/Relic-Game-Tool/issues
Platform: UNKNOWN
Classifier: Programming Language :: Python :: 3
Classifier: License :: OSI Approved :: GNU General Public License v3 (GPLv3)
Requires-Python: >=3.9
License-File: LICENSE.txt
Requires-Dist: mak-serialization-tools
